PyPrintful-1.0.0.dist-info/DESCRIPTION.rst
PyPrintful-1.0.0.dist-info/METADATA
PyPrintful-1.0.0.dist-info/RECORD
PyPrintful-1.0.0.dist-info/WHEEL
PyPrintful-1.0.0.dist-info/metadata.json
PyPrintful-1.0.0.dist-info/top_level.txt
pyPrintful/__init__.py
